event_dispatcher/__init__.py
event_dispatcher/_dispatcher.py
event_dispatcher/async_dispatcher.py
event_dispatcher/sync_dispatcher.py
event_dispatcher/types.py
event_dispatching-0.2.0.dist-info/LICENSE
event_dispatching-0.2.0.dist-info/METADATA
event_dispatching-0.2.0.dist-info/WHEEL
event_dispatching-0.2.0.dist-info/RECORD
