Metadata-Version: 2.1
Name: event-dispatching
Version: 0.2.0
Summary: Pure python implementation of event dispatcher
Home-page: https://github.com/trabem/event-dispatcher
License: MIT
Keywords: event-dispatcher,event-dispatching,events,event handling,python,asynchronous,event-driven,event management
Author: Ruslan Saiko
Author-email: ruslan.saiko.dev@gmail.com
Requires-Python: >=3.8,<4.0
Classifier: Intended Audience :: Developers
Classifier: License :: OSI Approved :: MIT License
Classifier: Programming Language :: Python
Classifier: Programming Language :: Python :: 3
Classifier: Programming Language :: Python :: 3.8
Classifier: Programming Language :: Python :: 3.9
Classifier: Programming Language :: Python :: 3.10
Classifier: Programming Language :: Python :: 3.11
Classifier: Topic :: Software Development
Classifier: Topic :: Software Development :: Libraries :: Python Modules
Project-URL: Repository, https://github.com/trabem/event-dispatcher
